MANIFEST.in
README.rst
setup.cfg
setup.py
tw2/__init__.py
tw2.pygmentize.egg-info/PKG-INFO
tw2.pygmentize.egg-info/SOURCES.txt
tw2.pygmentize.egg-info/dependency_links.txt
tw2.pygmentize.egg-info/entry_points.txt
tw2.pygmentize.egg-info/namespace_packages.txt
tw2.pygmentize.egg-info/not-zip-safe
tw2.pygmentize.egg-info/requires.txt
tw2.pygmentize.egg-info/top_level.txt
tw2/pygmentize/__init__.py
tw2/pygmentize/samples.py
tw2/pygmentize/widgets.py
tw2/pygmentize/templates/__init__.py
tw2/pygmentize/templates/pygmentize.mak