Metadata-Version: 1.1
Name: tw2.pygmentize
Version: 0.2
Summary: Syntax Highlighting using Pygments within a ToscaWidgets2 widget
Home-page: https://github.com/moschlar/tw2.pygmentize
Author: Moritz Schlarb
Author-email: moschlar@metalabs.de
License: UNKNOWN
Keywords: toscawidgets.widgets
Platform: UNKNOWN
Classifier: Development Status :: 4 - Beta
Classifier: Environment :: Web Environment
Classifier: Environment :: Web Environment :: ToscaWidgets
Classifier: Topic :: Software Development :: Libraries :: Python Modules
Classifier: Topic :: Software Development :: Widget Sets
Classifier: Intended Audience :: Developers
Classifier: Operating System :: OS Independent
Classifier: Programming Language :: Python
